{
  "data": [
    {
      "metric": "Revenue",
      "source_name": "revenue",
      "y-4": "4,398,000,000.0000",
      "y-3": "4,820,000,000.0000",
      "y-2": "5,050,000,000.0000",
      "y-1": "5,106,000,000.0000",
      "y": "4,699,000,000.0000",
      "fmt": "major",
      "desc": "The money generated from normal business operations. It is the top line (or gross income) figure from which costs are subtracted to determine net income.",
      "delta1": "-7.97%",
      "delta2": "1.11%",
      "delta3": "4.77%",
      "delta4": "9.60%",
      "deta3": "-2.01%"
    },
    {
      "metric": "Gross Profit",
      "source_name": "gp",
      "y-4": "3,573,000,000.0000",
      "y-3": "3,977,000,000.0000",
      "y-2": "4,111,000,000.0000",
      "y-1": "4,200,000,000.0000",
      "y": "3,796,000,000.0000",
      "fmt": "minor",
      "desc": "Revenue minus Cogs",
      "delta1": "-9.62%",
      "delta2": "2.16%",
      "delta3": "3.37%",
      "delta4": "11.31%",
      "deta3": "-2.01%"
    },
    {
      "metric": "Operating Expense",
      "source_name": "opex",
      "y-4": "2,028,000,000.0000",
      "y-3": "2,046,000,000.0000",
      "y-2": "2,176,000,000.0000",
      "y-1": "2,161,000,000.0000",
      "y": "2,032,000,000.0000",
      "fmt": "minor",
      "delta1": "-5.97%",
      "delta2": "-0.69%",
      "delta3": "6.35%",
      "delta4": "0.89%",
      "deta3": "4.44%"
    },
    {
      "metric": "Operating Income",
      "source_name": "opinc",
      "y-4": "1,545,000,000.0000",
      "y-3": "1,931,000,000.0000",
      "y-2": "1,935,000,000.0000",
      "y-1": "2,039,000,000.0000",
      "y": "1,764,000,000.0000",
      "fmt": "major",
      "desc": "it doesn't include one-off items such as interest or taxes that may skew a company's profit in a given year.The key difference between EBIT and operating income is that operating income does not include non-operating income, non-operating expenses, or other income.Operating income shows how much profit a company generates from its operations alone without interest or tax expenses.",
      "delta1": "-13.49%",
      "delta2": "5.37%",
      "delta3": "0.21%",
      "delta4": "24.98%",
      "deta3": "-47.10%"
    },
    {
      "metric": "Operating Margin",
      "source_name": "opp margin",
      "y-4": "35.1300",
      "y-3": "40.0600",
      "y-2": "38.3200",
      "y-1": "39.9300",
      "y": "37.5400",
      "fmt": "metric",
      "desc": "operating income / revenue",
      "delta1": "-5.99%",
      "delta2": "4.20%",
      "delta3": "-4.34%",
      "delta4": "14.03%",
      "deta3": "-47.10%"
    },
    {
      "metric": "Adjusted Operating Income",
      "source_name": "adj oppinc",
      "y-4": "1,572,000,000.0000",
      "y-3": "2,084,000,000.0000",
      "y-2": "2,247,000,000.0000",
      "y-1": "2,171,000,000.0000",
      "y": "1,753,000,000.0000",
      "fmt": "minor",
      "desc": "Ebit + r&d",
      "delta1": "-19.25%",
      "delta2": "-3.38%",
      "delta3": "7.82%",
      "delta4": "32.57%"
    },
    {
      "metric": "EBIT",
      "source_name": "ebit",
      "y-4": "1,572,000,000.0000",
      "y-3": "2,084,000,000.0000",
      "y-2": "2,247,000,000.0000",
      "y-1": "2,171,000,000.0000",
      "y": "1,753,000,000.0000",
      "fmt": "major",
      "desc": "a company may have interest income such as credit financing, which EBIT would capture, while operating income would not capture interest income. Also, EBIT strips out the cost of debt (or interest expense), which is deducted from revenue to arrive at net income. By adding back interest expense to net income to arrive at EBIT, we can see net income without the cost of debt. ",
      "delta1": "-19.25%",
      "delta2": "-3.38%",
      "delta3": "7.82%",
      "delta4": "32.57%",
      "deta3": "-47.10%"
    },
    {
      "metric": "interest expense",
      "source_name": "intexp",
      "y-4": "55,000,000.0000",
      "y-3": "52,000,000.0000",
      "y-2": "48,000,000.0000",
      "y-1": "50,000,000.0000",
      "y": "54,000,000.0000",
      "fmt": "minor",
      "delta1": "8.00%",
      "delta2": "4.17%",
      "delta3": "-7.69%",
      "delta4": "-5.45%",
      "deta3": "13.33%"
    },
    {
      "metric": "EBT",
      "source_name": "ebt",
      "y-4": "1,517,000,000.0000",
      "y-3": "2,032,000,000.0000",
      "y-2": "2,199,000,000.0000",
      "y-1": "2,121,000,000.0000",
      "y": "1,699,000,000.0000",
      "fmt": "major",
      "delta1": "-19.90%",
      "delta2": "-3.55%",
      "delta3": "8.22%",
      "delta4": "33.95%",
      "deta3": "13.33%"
    },
    {
      "metric": "tax expense",
      "source_name": "taxexp",
      "y-4": "318,000,000.0000",
      "y-3": "654,000,000.0000",
      "y-2": "518,000,000.0000",
      "y-1": "478,000,000.0000",
      "y": "263,000,000.0000",
      "fmt": "minor",
      "delta1": "-44.98%",
      "delta2": "-7.72%",
      "delta3": "-20.80%",
      "delta4": "105.66%",
      "deta3": "33.06%"
    },
    {
      "metric": "Net Income",
      "source_name": "netinc",
      "y-4": "1,199,000,000.0000",
      "y-3": "1,378,000,000.0000",
      "y-2": "1,681,000,000.0000",
      "y-1": "1,643,000,000.0000",
      "y": "1,436,000,000.0000",
      "fmt": "major",
      "desc": "all expenses, interest, and taxes have been subtracted from revenues.",
      "delta1": "-12.60%",
      "delta2": "-2.26%",
      "delta3": "21.99%",
      "delta4": "14.93%",
      "deta3": "-59.42%"
    },
    {
      "metric": "Adjusted Net Income",
      "source_name": "adj netinc",
      "y-4": "1,199,000,000.0000",
      "y-3": "1,378,000,000.0000",
      "y-2": "1,681,000,000.0000",
      "y-1": "1,643,000,000.0000",
      "y": "1,436,000,000.0000",
      "fmt": "minor",
      "desc": "Net Income + R&D",
      "delta1": "-12.60%",
      "delta2": "-2.26%",
      "delta3": "21.99%",
      "delta4": "14.93%"
    },
    {
      "metric": "Depreciation and Amortization",
      "source_name": "depamor",
      "y-4": "128,000,000.0000",
      "y-3": "133,000,000.0000",
      "y-2": "145,000,000.0000",
      "y-1": "153,000,000.0000",
      "y": "140,000,000.0000",
      "fmt": "minor",
      "desc": "depreciation is considered an operating expense",
      "delta1": "-8.50%",
      "delta2": "5.52%",
      "delta3": "9.02%",
      "delta4": "3.91%",
      "deta3": "11.32%"
    },
    {
      "metric": "EBITDA",
      "source_name": "ebitda",
      "y-4": "1,700,000,000.0000",
      "y-3": "2,217,000,000.0000",
      "y-2": "2,392,000,000.0000",
      "y-1": "2,324,000,000.0000",
      "y": "1,893,000,000.0000",
      "fmt": "major",
      "delta1": "-18.55%",
      "delta2": "-2.84%",
      "delta3": "7.89%",
      "delta4": "30.41%",
      "deta3": "-19.67%"
    },
    {
      "metric": "Effective Tax Rate",
      "source_name": "tax rate",
      "y-4": "20.9600",
      "y-3": "32.1900",
      "y-2": "23.5600",
      "y-1": "22.5400",
      "y": "15.4800",
      "fmt": "metric",
      "desc": "tax expense divided by (ebit plus interest expense)",
      "delta4": "53.58%",
      "delta3": "-26.81%",
      "delta2": "-4.33%",
      "delta1": "-31.32%"
    },
    {
      "metric": "NOPAT",
      "source_name": "nopat",
      "y-4": "1,221,168,000.0000",
      "y-3": "1,309,411,100.0000",
      "y-2": "1,479,114,000.0000",
      "y-1": "1,579,409,400.0000",
      "y": "1,490,932,800.0000",
      "fmt": "major",
      "desc": "(df['opinc']) * (1-df['tax rate']/100)",
      "delta4": "7.23%",
      "delta3": "12.96%",
      "delta2": "6.78%",
      "delta1": "-5.60%"
    },
    {
      "metric": "Retained Earnings",
      "source_name": "retearn",
      "y-4": "24,872,000,000.0000",
      "y-3": "25,620,000,000.0000",
      "y-2": "26,672,000,000.0000",
      "y-1": "27,688,000,000.0000",
      "y": "28,338,000,000.0000",
      "fmt": "minor",
      "desc": "netincome + dividend payments",
      "delta4": "3.01%",
      "delta3": "4.11%",
      "delta2": "3.81%",
      "delta1": "2.35%"
    }
  ]
}